codesecdirectunlic/__init__.py
codesecdirectunlic/module1.py
codesecdirectunlic-0.1.0.dist-info/LICENSE
codesecdirectunlic-0.1.0.dist-info/METADATA
codesecdirectunlic-0.1.0.dist-info/WHEEL
codesecdirectunlic-0.1.0.dist-info/top_level.txt
codesecdirectunlic-0.1.0.dist-info/RECORD
