Metadata-Version: 2.1
Name: codesecdirectunlic
Version: 0.1.0
Summary: A sample Python package
Author-email: Your Name <you@example.com>
License: Unlicense
Project-URL: Homepage, https://github.com/james-0131-2/pycodesecdirectunlic
Project-URL: Repository, https://github.com/james-0131-2/pycodesecdirectunlic
Requires-Python: >=3.7
License-File: LICENSE
Requires-Dist: requests
